dbFast/__init__.py
dbFast/db.py
dbfast-0.4.dist-info/METADATA
dbfast-0.4.dist-info/WHEEL
dbfast-0.4.dist-info/top_level.txt
dbfast-0.4.dist-info/RECORD
