Metadata-Version: 2.4
Name: dbFast
Version: 0.4
Summary: my own library for Fast database
Author: Vanja Nazarenko
Requires-Dist: sqlalchemy
Dynamic: author
Dynamic: requires-dist
Dynamic: summary
